{
  "type": "Feature",
  "properties": {
    "gn:asciiname":"Kooddoo Atoll",
    "gn:country_code":"MV",
    "gn:dem":6,
    "gn:feature_class":"P",
    "gn:feature_code":"PPLL",
    "gn:name":"Kooddoo Atoll",
    "gn:population":0,
    "gn:timezone":"Indian/Maldives",
    "iso:country":"MV",
    "name:eng_x_preferred":[
        "Kooddoo Atoll"
    ],
    "wof:name":"Kooddoo Atoll",
    "wof:placetype":"locality"
},
  "geometry": {"coordinates":[73.43162,0.73769],"type":"Point"}
}