{
  "type": "Feature",
  "properties": {
    "gn:admin1_code":"05",
    "gn:asciiname":"Kunahandhoo",
    "gn:country_code":"MV",
    "gn:dem":7,
    "gn:feature_class":"P",
    "gn:feature_code":"PPL",
    "gn:name":"Kunahandhoo",
    "gn:population":0,
    "gn:timezone":"Indian/Maldives",
    "iso:country":"MV",
    "wof:name":"Kunahandhoo",
    "wof:placetype":"locality"
},
  "geometry": {"coordinates":[73.36739,1.78276],"type":"Point"}
}