{
  "type": "Feature",
  "properties": {
    "gn:admin1_code":"01",
    "gn:asciiname":"Hulhudhoo",
    "gn:country_code":"MV",
    "gn:dem":8,
    "gn:feature_class":"P",
    "gn:feature_code":"PPL",
    "gn:name":"Hulhudhoo",
    "gn:population":0,
    "gn:timezone":"Indian/Maldives",
    "iso:country":"MV",
    "name:ceb_x_preferred":[
        "Hulhudhoo"
    ],
    "name:nld_x_preferred":[
        "Hulhudhoo"
    ],
    "name:swe_x_preferred":[
        "Hulhudhoo"
    ],
    "wof:name":"Hulhudhoo",
    "wof:placetype":"locality"
},
  "geometry": {"coordinates":[73.22787,-0.59278],"type":"Point"}
}