{
  "type": "Feature",
  "properties": {
    "gn:country":"MV",
    "gn:fcode":"ISL",
    "gn:population":700,
    "iso:country":"MV",
    "name:ceb_x_preferred":[
        "Sun Island"
    ],
    "name:swe_x_preferred":[
        "Sun Island"
    ],
    "qs:name":"Sun Island",
    "qs:photos_9r":0,
    "qs:photos_sr":0,
    "qs:pop_sr":"2",
    "wof:name":"Sun Island",
    "wof:placetype":"locality",
    "wof:population":700
},
  "geometry": {"coordinates":[72.80141999999999,3.48344],"type":"Point"}
}