{
  "type": "Feature",
  "properties": {
    "gn:asciiname":"Thulusdhoo",
    "gn:country_code":"MV",
    "gn:dem":7,
    "gn:feature_class":"P",
    "gn:feature_code":"PPL",
    "gn:name":"Thulusdhoo",
    "gn:population":0,
    "gn:timezone":"Indian/Maldives",
    "iso:country":"MV",
    "wof:name":"Thulusdhoo",
    "wof:placetype":"locality"
},
  "geometry": {"coordinates":[73.65269000000001,4.37421],"type":"Point"}
}