{
  "type": "Feature",
  "properties": {
    "gn:admin1_code":"38",
    "gn:asciiname":"Guraidhoo",
    "gn:country_code":"MV",
    "gn:dem":-1,
    "gn:elevation":"1.0",
    "gn:feature_class":"P",
    "gn:feature_code":"PPL",
    "gn:name":"Guraidhoo",
    "gn:population":1800,
    "gn:timezone":"Indian/Maldives",
    "iso:country":"MV",
    "wof:name":"Guraidhoo",
    "wof:placetype":"locality",
    "wof:population":1800
},
  "geometry": {"coordinates":[73.46623000000002,3.90045],"type":"Point"}
}