{
  "type": "Feature",
  "properties": {
    "gn:asciiname":"Vaikaradhoo",
    "gn:country_code":"MV",
    "gn:dem":10,
    "gn:feature_class":"P",
    "gn:feature_code":"PPL",
    "gn:name":"Vaikaradhoo",
    "gn:population":0,
    "gn:timezone":"Indian/Maldives",
    "iso:country":"MV",
    "wof:name":"Vaikaradhoo",
    "wof:placetype":"locality"
},
  "geometry": {"coordinates":[72.95350999999999,6.55053],"type":"Point"}
}