{
  "type": "Feature",
  "properties": {
    "gn:asciiname":"Ari Atoll",
    "gn:country_code":"MV",
    "gn:dem":-9999,
    "gn:feature_class":"P",
    "gn:feature_code":"PPL",
    "gn:name":"Ari Atoll",
    "gn:population":0,
    "gn:timezone":"Indian/Maldives",
    "iso:country":"MV",
    "name:ceb_x_preferred":[
        "Ari Atoll"
    ],
    "name:deu_x_preferred":[
        "Ari-Atoll"
    ],
    "name:fra_x_preferred":[
        "Ari"
    ],
    "name:nld_x_preferred":[
        "Ari-atol"
    ],
    "name:zho_x_preferred":[
        "\u4e9e\u91cc\u74b0\u7901"
    ],
    "wof:name":"Ari Atoll",
    "wof:placetype":"locality"
},
  "geometry": {"coordinates":[72.83189,3.88244],"type":"Point"}
}