{
  "type": "Feature",
  "properties": {
    "gn:asciiname":"Maamendhoo",
    "gn:country_code":"MV",
    "gn:dem":8,
    "gn:feature_class":"P",
    "gn:feature_code":"PPL",
    "gn:name":"Maamendhoo",
    "gn:population":0,
    "gn:timezone":"Indian/Maldives",
    "iso:country":"MV",
    "name:nld_x_preferred":[
        "Maamendhoo"
    ],
    "name:slk_x_preferred":[
        "M\u00e1mend\u00fa"
    ],
    "wof:name":"Maamendhoo",
    "wof:placetype":"locality"
},
  "geometry": {"coordinates":[73.38919,1.81682],"type":"Point"}
}