{
  "type": "Feature",
  "properties": {
    "gn:asciiname":"Dharavandhoo",
    "gn:country_code":"MV",
    "gn:dem":7,
    "gn:feature_class":"P",
    "gn:feature_code":"PPL",
    "gn:name":"Dharavandhoo",
    "gn:population":0,
    "gn:timezone":"Indian/Maldives",
    "iso:country":"MV",
    "name:eng_x_preferred":[
        "Dharavandhoo"
    ],
    "wof:name":"Dharavandhoo",
    "wof:placetype":"locality"
},
  "geometry": {"coordinates":[73.13256,5.15825],"type":"Point"}
}