{
  "type": "Feature",
  "properties": {
    "gn:admin1_code":"34",
    "gn:asciiname":"Viligili",
    "gn:country_code":"MV",
    "gn:dem":5,
    "gn:feature_class":"P",
    "gn:feature_code":"PPLA",
    "gn:name":"Viligili",
    "gn:population":2925,
    "gn:timezone":"Indian/Maldives",
    "iso:country":"MV",
    "name:und_x_variant":[
        "Villingili",
        "Viligili"
    ],
    "wof:name":"Viligili",
    "wof:placetype":"locality",
    "wof:population":2925
},
  "geometry": {"coordinates":[73.43295999999999,0.75906],"type":"Point"}
}