{
  "type": "Feature",
  "properties": {
    "gn:country":"MV",
    "gn:fcode":"PPL",
    "gn:population":2156,
    "iso:country":"MV",
    "name:ceb_x_preferred":[
        "Mahibadhoo"
    ],
    "name:deu_x_preferred":[
        "Mahibadhoo"
    ],
    "name:div_x_preferred":[
        "\u0789\u07a6\u0780\u07a8\u0784\u07a6\u078b\u07ab"
    ],
    "name:eng_x_preferred":[
        "Mahibadhoo"
    ],
    "name:fas_x_preferred":[
        "\u0645\u0627\u0647\u06cc\u0628\u0627\u062f\u0647\u0648"
    ],
    "name:ita_x_preferred":[
        "Mahibadhoo"
    ],
    "name:jpn_x_preferred":[
        "\u30de\u30d2\u30d0\u30c9\u30db\u30fc"
    ],
    "name:nld_x_preferred":[
        "Mahibadhoo"
    ],
    "name:pol_x_preferred":[
        "Mahibadhoo"
    ],
    "name:slk_x_preferred":[
        "Mahibad\u00fa"
    ],
    "name:swe_x_preferred":[
        "Mahibadhoo"
    ],
    "qs:name":"Mahibadhoo",
    "qs:photos_9r":0,
    "qs:photos_sr":0,
    "qs:pop_sr":"4",
    "wd:wordcount":274,
    "wof:name":"Mahibadhoo",
    "wof:placetype":"locality",
    "wof:population":2156
},
  "geometry": {"coordinates":[72.96666999999999,3.78333],"type":"Point"}
}