{
  "type": "Feature",
  "properties": {
    "gn:asciiname":"Kanu Huraa",
    "gn:country_code":"MV",
    "gn:dem":2,
    "gn:feature_class":"P",
    "gn:feature_code":"PPL",
    "gn:name":"Kanu Huraa",
    "gn:population":0,
    "gn:timezone":"Indian/Maldives",
    "iso:country":"MV",
    "wof:name":"Kanu Huraa",
    "wof:placetype":"locality"
},
  "geometry": {"coordinates":[73.59175,4.3183],"type":"Point"}
}