{
  "type": "Feature",
  "properties": {
    "gn:country":"MV",
    "gn:fcode":"PPLL",
    "gn:pop":1258,
    "iso:country":"MV",
    "qs:name":"Open Stage",
    "qs:photos_9r":0,
    "qs:photos_sr":0,
    "qs:pop_sr":"3",
    "wof:name":"Open Stage",
    "wof:placetype":"locality",
    "wof:population":1258
},
  "geometry": {"coordinates":[73.07115,5.1053],"type":"Point"}
}