{
  "type": "Feature",
  "properties": {
    "gn:country":"MV",
    "gn:fcode":"PPL",
    "gn:population":541,
    "iso:country":"MV",
    "name:ceb_x_preferred":[
        "Felidhoo"
    ],
    "name:div_x_preferred":[
        "\u078a\u07ac\u078d\u07a8\u078b\u07ab"
    ],
    "name:eng_x_preferred":[
        "Felidhoo"
    ],
    "name:fas_x_preferred":[
        "\u0641\u0644\u06cc\u062f\u0647\u0648"
    ],
    "name:jpn_x_preferred":[
        "\u30d5\u30a7\u30ea\u30c9\u30a5\u30fc"
    ],
    "name:nld_x_preferred":[
        "Felidhoo"
    ],
    "name:slk_x_preferred":[
        "Felid\u00fa"
    ],
    "name:spa_x_preferred":[
        "Felidhoo"
    ],
    "name:swe_x_preferred":[
        "Felidhoo"
    ],
    "qs_pg:aaroncc":"MV",
    "qs_pg:gn_country":"MV",
    "qs_pg:gn_fcode":"PPL",
    "qs_pg:gn_pop":541,
    "qs_pg:name":"Felidhoo",
    "qs_pg:photos_9r":0,
    "qs_pg:photos_sr":0,
    "qs_pg:pop_sr":2,
    "qs_pg:qs_pg_placetype":"locality",
    "wof:name":"Felidhoo",
    "wof:placetype":"locality",
    "wof:population":541
},
  "geometry": {"coordinates":[73.53333000000001,3.48333],"type":"Point"}
}