{
  "type": "Feature",
  "properties": {
    "gn:country":"MV",
    "gn:fcode":"PPL",
    "gn:pop":2808,
    "iso:country":"MV",
    "name:div_x_preferred":[
        "\u0787\u07ad\u078b\u07a6\u078a\u07aa\u0781\u07a8"
    ],
    "name:ell_x_preferred":[
        "\u0395\u03ca\u03bd\u03c4\u03c7\u03b1\u03c6\u03bf\u03cd\u03c3\u03b9"
    ],
    "name:eng_x_preferred":[
        "Eydhafushi"
    ],
    "name:nld_x_preferred":[
        "Eydhafushi"
    ],
    "name:pol_x_preferred":[
        "Eydhafushi"
    ],
    "name:rus_x_preferred":[
        "\u042d\u0439\u0434\u0445\u0430\u0444\u0443\u0448\u0438"
    ],
    "name:slk_x_preferred":[
        "\u00c9dafusi"
    ],
    "name:spa_x_preferred":[
        "Eydhafushi"
    ],
    "name:swe_x_preferred":[
        "Eydhafushi"
    ],
    "qs:name":"Eydhafushi",
    "qs:photos_9r":0,
    "qs:photos_sr":0,
    "qs:pop_sr":"4",
    "wd:wordcount":9,
    "wof:name":"Eydhafushi",
    "wof:placetype":"locality",
    "wof:population":2808
},
  "geometry": {"coordinates":[73.07078,5.10327],"type":"Point"}
}