{
  "type": "Feature",
  "properties": {
    "gn:asciiname":"Kamadhoo",
    "gn:country_code":"MV",
    "gn:dem":14,
    "gn:feature_class":"P",
    "gn:feature_code":"PPL",
    "gn:name":"Kamadhoo",
    "gn:population":0,
    "gn:timezone":"Indian/Maldives",
    "iso:country":"MV",
    "wof:name":"Kamadhoo",
    "wof:placetype":"locality"
},
  "geometry": {"coordinates":[73.1371,5.28105],"type":"Point"}
}