{
  "type": "Feature",
  "properties": {
    "gn:asciiname":"Kamadhoo",
    "gn:country_code":"MV",
    "gn:dem":14,
    "gn:feature_class":"P",
    "gn:feature_code":"PPL",
    "gn:name":"Kamadhoo",
    "gn:population":0,
    "gn:timezone":"Indian/Maldives",
    "iso:country":"MV",
    "name:ceb_x_preferred":[
        "Kamadhoo"
    ],
    "name:div_x_preferred":[
        "\u0786\u07a6\u0789\u07a6\u078b\u07ab"
    ],
    "name:nld_x_preferred":[
        "Kamadhoo"
    ],
    "name:sin_x_preferred":[
        "\u0d9a\u0db8\u0dcf\u0daf\u0dd6"
    ],
    "name:slk_x_preferred":[
        "Kamad\u00fa"
    ],
    "name:swe_x_preferred":[
        "Kamadhoo"
    ],
    "wof:name":"Kamadhoo",
    "wof:placetype":"locality"
},
  "geometry": {"coordinates":[73.1371,5.28105],"type":"Point"}
}